{
  "users": [
    {
      "id": "13d4",
      "name": "jenm",
      "mobile": "90924321",
      "email": "Bhavikpatel773241@gmail.com",
      "marks": "21",
      "status": "pass"
    },
    {
      "id": "30e6",
      "name": "jenm",
      "mobile": "90924321",
      "email": "Bhavikpatel773241@gmail.com",
      "marks": "21",
      "status": "fail"
    },
    {
      "id": "b85b",
      "name": "jenm",
      "mobile": "90924321",
      "email": "Bhavikpatel773241@gmail.com",
      "marks": "21",
      "status": "fail"
    },
    {
      "id": "081f",
      "name": "jenzzzzzzzzzzz",
      "mobile": "90924321",
      "email": "Bhavikpatel773241@gmail.com",
      "marks": "21",
      "status": "fail"
    },
    {
      "id": "1a97",
      "name": "jenm",
      "mobile": "90924321",
      "email": "Bhavikpatel773241@gmail.com",
      "marks": "21",
      "status": "fail"
    }
  ]
}